cse163_utils/__init__.py
cse163_utils/data.py
cse163_utils/imgd.py
cse163_utils/testing.py
cse163_utils-0.1.2.dist-info/WHEEL
cse163_utils-0.1.2.dist-info/METADATA
cse163_utils-0.1.2.dist-info/RECORD
