Metadata-Version: 2.1
Name: cse163-utils
Version: 0.1.2
Summary: Useful helper functions for CSE 163: Intermediate Data Programming course content. https://cse163.github.io/book/
Home-page: https://cse163.github.io/book/#
License: MIT
Author: Hunter Schafer
Author-email: hschafer@cs.washington.edu
Requires-Python: >=3.8,<3.11
Classifier: License :: OSI Approved :: MIT License
Classifier: Programming Language :: Python :: 3
Classifier: Programming Language :: Python :: 3.10
Classifier: Programming Language :: Python :: 3.8
Classifier: Programming Language :: Python :: 3.9
Requires-Dist: descartes (>=1.1.0,<2.0.0)
Requires-Dist: flake8 (>=4.0.1,<5.0.0)
Requires-Dist: geopandas (>=0.10.2,<0.11.0)
Requires-Dist: matplotlib (>=3.5.1,<4.0.0)
Requires-Dist: mock (>=4.0.3,<5.0.0)
Requires-Dist: numpy (>=1.22.2,<2.0.0)
Requires-Dist: pandas (>=1.4.1,<2.0.0)
Requires-Dist: requests (>=2.27.1,<3.0.0)
Requires-Dist: scikit-image (>=0.19.2,<0.20.0)
Requires-Dist: scikit-learn (>=1.0.2,<2.0.0)
Requires-Dist: scipy (>=1.8.0,<2.0.0)
Requires-Dist: seaborn (>=0.11.2,<0.12.0)
Project-URL: Documentation, https://github.com/cse163/cse163_utils
Project-URL: Repository, https://github.com/cse163/cse163_utils
